three_backup/__init__.py
three_backup/backup_object.py
three_backup/backup_object_id.py
three_backup/backup_object_type.py
three_backup/backup_stage.py
three_backup/bash_cmd.py
three_backup/cli.py
three_backup/config_manager.py
three_backup/discovery.py
three_backup/fnmatch.py
three_backup/remote_storage.py
three_backup/implementations/__init__.py
three_backup/implementations/clickhouse.py
three_backup/implementations/lxd.py
three_backup/implementations/postgres.py
three_backup/implementations/zfs.py
three_backup/remote_storages/__init__.py
three_backup/remote_storages/filesystem.py
three_backup/remote_storages/s3.py
three_backup-0.1.1.dist-info/METADATA
three_backup-0.1.1.dist-info/WHEEL
three_backup-0.1.1.dist-info/entry_points.txt
three_backup-0.1.1.dist-info/RECORD
