Metadata-Version: 2.4
Name: three_backup
Version: 0.1.1
Summary: Unified incremental backup tool for LXD, PostgreSQL, and ClickHouse
Author-email: Your Name <your.email@example.com>
License: MIT
Requires-Python: >=3.8
Requires-Dist: boto3>=1.26.0
Requires-Dist: click>=8.0.0
Requires-Dist: croniter>=2.0.0
Requires-Dist: python-dotenv>=1.0.0
Requires-Dist: pyyaml>=6.0.0
Requires-Dist: s3cmd>=2.0.0
Requires-Dist: tqdm>=4.65.0
Requires-Dist: wcmatch>=10.0
